LICENSE
MANIFEST.in
README.md
setup.py
xmlunittest.py
xmlunittestbetter.egg-info/PKG-INFO
xmlunittestbetter.egg-info/SOURCES.txt
xmlunittestbetter.egg-info/dependency_links.txt
xmlunittestbetter.egg-info/requires.txt
xmlunittestbetter.egg-info/top_level.txt