Metadata-Version: 1.1
Name: xmlunittestbetter
Version: 0.1
Summary: Library using lxml and unittest for unit testing XML. This is an actively maintained and PEP8 compliant fork of xmlunittest.
Home-page: https://github.com/richardasaurus/python-xmlunittest-better
Author: Richard O'Dwyer
Author-email: richard@richard.do
License: MIT
Platform: UNKNOWN
Classifier: Development Status :: 4 - Beta
Classifier: Intended Audience :: Developers
Classifier: License :: OSI Approved :: MIT License
Classifier: Programming Language :: Python :: 2.7
Classifier: Programming Language :: Python :: 3.3
Classifier: Programming Language :: Python :: 3.4
Classifier: Topic :: Software Development :: Libraries :: Python Modules
Classifier: Topic :: Software Development :: Testing
Classifier: Topic :: Text Processing :: Markup :: XML
